{
  "date": "2026-06-26",
  "flights": [
    {
      "time": "00:05",
      "datetime": "2026-06-26T00:05:00",
      "gate": "D16",
      "flight_code": "JX12",
      "airline_code": "JX",
      "airline_name": "星宇航空",
      "type": "departure",
      "airport_code": "SFO",
      "city": "San Francisco",
      "status": "出發DEPARTED",
      "aircraft": "A350-900",
      "terminal": "2",
      "destination": "San Francisco (SFO)",
      "codeshare_flights": []
    },
    {
      "time": "00:10",
      "datetime": "2026-06-26T00:10:00",
      "gate": "D15R",
      "flight_code": "JX2",
      "airline_code": "JX",
      "airline_name": "星宇航空",
      "type": "departure",
      "airport_code": "LAX",
      "city": "Los Angeles",
      "status": "出發DEPARTED",
      "aircraft": "A350-900",
      "terminal": "2",
      "destination": "Los Angeles (LAX)",
      "codeshare_flights": []
    },
    {
      "time": "06:20",
      "datetime": "2026-06-26T06:20:00",
      "gate": "D13",
      "flight_code": "BR134",
      "airline_code": "BR",
      "airline_name": "長榮航空",
      "type": "departure",
      "airport_code": "UKB",
      "city": "KOBE",
      "status": "出發DEPARTED",
      "aircraft": "A321-200",
      "terminal": "2",
      "destination": "KOBE (UKB)",
      "codeshare_flights": []
    },
    {
      "time": "06:30",
      "datetime": "2026-06-26T06:30:00",
      "gate": "D17",
      "flight_code": "BR217",
      "airline_code": "BR",
      "airline_name": "長榮航空",
      "type": "departure",
      "airport_code": "KUL",
      "city": "Kuala Lumpur",
      "status": "出發DEPARTED",
      "aircraft": "B777-300",
      "terminal": "2",
      "destination": "Kuala Lumpur (KUL)",
      "codeshare_flights": [
        {
          "flight_code": "TK9457",
          "airline_code": "TK",
          "airline_name": "土耳其航空"
        }
      ]
    },
    {
      "time": "06:55",
      "datetime": "2026-06-26T06:55:00",
      "gate": "D18",
      "flight_code": "JX761",
      "airline_code": "JX",
      "airline_name": "星宇航空",
      "type": "departure",
      "airport_code": "CGK",
      "city": "Jakarta",
      "status": "出發DEPARTED",
      "aircraft": "A321-252",
      "terminal": "2",
      "destination": "Jakarta (CGK)",
      "codeshare_flights": []
    },
    {
      "time": "07:00",
      "datetime": "2026-06-26T07:00:00",
      "gate": "D15R",
      "flight_code": "BR891",
      "airline_code": "BR",
      "airline_name": "長榮航空",
      "type": "departure",
      "airport_code": "HKG",
      "city": "Hong Kong",
      "status": "出發DEPARTED",
      "aircraft": "B787-10",
      "terminal": "2",
      "destination": "Hong Kong (HKG)",
      "codeshare_flights": [
        {
          "flight_code": "HX1819",
          "airline_code": "HX",
          "airline_name": "香港航空"
        }
      ]
    },
    {
      "time": "07:30",
      "datetime": "2026-06-26T07:30:00",
      "gate": "D13",
      "flight_code": "CI154",
      "airline_code": "CI",
      "airline_name": "中華航空",
      "type": "departure",
      "airport_code": "NGO",
      "city": "Nagoya",
      "status": "出發DEPARTED",
      "aircraft": "A321-271",
      "terminal": "2",
      "destination": "Nagoya (NGO)",
      "codeshare_flights": [
        {
          "flight_code": "JL5112",
          "airline_code": "JL",
          "airline_name": "日本航空"
        }
      ]
    },
    {
      "time": "07:30",
      "datetime": "2026-06-26T07:30:00",
      "gate": "D16",
      "flight_code": "BR170",
      "airline_code": "BR",
      "airline_name": "長榮航空",
      "type": "departure",
      "airport_code": "ICN",
      "city": "Incheon",
      "status": "出發DEPARTED",
      "aircraft": "A330-300",
      "terminal": "2",
      "destination": "Incheon (ICN)",
      "codeshare_flights": [
        {
          "flight_code": "AC6535",
          "airline_code": "AC",
          "airline_name": "加拿大航空"
        },
        {
          "flight_code": "TG6396",
          "airline_code": "TG",
          "airline_name": "泰國航空"
        },
        {
          "flight_code": "OZ6874",
          "airline_code": "OZ",
          "airline_name": "韓亞航空"
        },
        {
          "flight_code": "NZ4926",
          "airline_code": "NZ",
          "airline_name": "紐西蘭航空"
        },
        {
          "flight_code": "B77028",
          "airline_code": "B7",
          "airline_name": "立榮航空"
        }
      ]
    },
    {
      "time": "08:10",
      "datetime": "2026-06-26T08:10:00",
      "gate": "D11",
      "flight_code": "JX771",
      "airline_code": "JX",
      "airline_name": "星宇航空",
      "type": "departure",
      "airport_code": "SIN",
      "city": "Singapore",
      "status": "出發DEPARTED",
      "aircraft": "A350-900",
      "terminal": "2",
      "destination": "Singapore (SIN)",
      "codeshare_flights": []
    },
    {
      "time": "08:15",
      "datetime": "2026-06-26T08:15:00",
      "gate": "D17",
      "flight_code": "BR851",
      "airline_code": "BR",
      "airline_name": "長榮航空",
      "type": "departure",
      "airport_code": "HKG",
      "city": "Hong Kong",
      "status": "出發DEPARTED",
      "aircraft": "B787-9",
      "terminal": "2",
      "destination": "Hong Kong (HKG)",
      "codeshare_flights": [
        {
          "flight_code": "HX1821",
          "airline_code": "HX",
          "airline_name": "香港航空"
        }
      ]
    },
    {
      "time": "08:20",
      "datetime": "2026-06-26T08:20:00",
      "gate": "D12",
      "flight_code": "BR132",
      "airline_code": "BR",
      "airline_name": "長榮航空",
      "type": "departure",
      "airport_code": "KIX",
      "city": "Osaka Kansai",
      "status": "出發DEPARTED",
      "aircraft": "B787-10",
      "terminal": "2",
      "destination": "Osaka Kansai (KIX)",
      "codeshare_flights": [
        {
          "flight_code": "TG6356",
          "airline_code": "TG",
          "airline_name": "泰國航空"
        },
        {
          "flight_code": "NH5812",
          "airline_code": "NH",
          "airline_name": "全日本空輸"
        },
        {
          "flight_code": "NZ4914",
          "airline_code": "NZ",
          "airline_name": "紐西蘭航空"
        }
      ]
    },
    {
      "time": "08:40",
      "datetime": "2026-06-26T08:40:00",
      "gate": "D15R",
      "flight_code": "CI501",
      "airline_code": "CI",
      "airline_name": "中華航空",
      "type": "departure",
      "airport_code": "PVG",
      "city": "Shanghai/Pudong",
      "status": "出發DEPARTED",
      "aircraft": "A350-900",
      "terminal": "2",
      "destination": "Shanghai/Pudong (PVG)",
      "codeshare_flights": [
        {
          "flight_code": "CZ7973",
          "airline_code": "CZ",
          "airline_name": "南方航空"
        },
        {
          "flight_code": "MU8901",
          "airline_code": "MU",
          "airline_name": "東方航空"
        }
      ]
    },
    {
      "time": "09:00",
      "datetime": "2026-06-26T09:00:00",
      "gate": "D18",
      "flight_code": "BR198",
      "airline_code": "BR",
      "airline_name": "長榮航空",
      "type": "departure",
      "airport_code": "NRT",
      "city": "Tokyo",
      "status": "出發DEPARTED",
      "aircraft": "B787-10",
      "terminal": "2",
      "destination": "Tokyo (NRT)",
      "codeshare_flights": [
        {
          "flight_code": "LO5344",
          "airline_code": "LO",
          "airline_name": "波蘭航空"
        },
        {
          "flight_code": "NZ4934",
          "airline_code": "NZ",
          "airline_name": "紐西蘭航空"
        },
        {
          "flight_code": "NH5808",
          "airline_code": "NH",
          "airline_name": "全日本空輸"
        },
        {
          "flight_code": "AC6543",
          "airline_code": "AC",
          "airline_name": "加拿大航空"
        },
        {
          "flight_code": "TG6346",
          "airline_code": "TG",
          "airline_name": "泰國航空"
        }
      ]
    },
    {
      "time": "09:00",
      "datetime": "2026-06-26T09:00:00",
      "gate": "D14R",
      "flight_code": "BR237",
      "airline_code": "BR",
      "airline_name": "長榮航空",
      "type": "departure",
      "airport_code": "CGK",
      "city": "Jakarta",
      "status": "出發DEPARTED",
      "aircraft": "B787-9",
      "terminal": "2",
      "destination": "Jakarta (CGK)",
      "codeshare_flights": []
    },
    {
      "time": "09:00",
      "datetime": "2026-06-26T09:00:00",
      "gate": "D16",
      "flight_code": "BR397",
      "airline_code": "BR",
      "airline_name": "長榮航空",
      "type": "departure",
      "airport_code": "HAN",
      "city": "Hanoi",
      "status": "出發DEPARTED",
      "aircraft": "B777-300",
      "terminal": "2",
      "destination": "Hanoi (HAN)",
      "codeshare_flights": []
    },
    {
      "time": "09:50",
      "datetime": "2026-06-26T09:50:00",
      "gate": "D11",
      "flight_code": "BR255",
      "airline_code": "BR",
      "airline_name": "長榮航空",
      "type": "departure",
      "airport_code": "DPS",
      "city": "Bali",
      "status": "出發DEPARTED",
      "aircraft": "A330-300",
      "terminal": "2",
      "destination": "Bali (DPS)",
      "codeshare_flights": []
    },
    {
      "time": "09:55",
      "datetime": "2026-06-26T09:55:00",
      "gate": "D12",
      "flight_code": "BR712",
      "airline_code": "BR",
      "airline_name": "長榮航空",
      "type": "departure",
      "airport_code": "PVG",
      "city": "Shanghai/Pudong",
      "status": "出發DEPARTED",
      "aircraft": "B777-300",
      "terminal": "2",
      "destination": "Shanghai/Pudong (PVG)",
      "codeshare_flights": [
        {
          "flight_code": "HO3182",
          "airline_code": "HO",
          "airline_name": "吉祥航空"
        },
        {
          "flight_code": "CA5512",
          "airline_code": "CA",
          "airline_name": "中國國際"
        },
        {
          "flight_code": "B77016",
          "airline_code": "B7",
          "airline_name": "立榮航空"
        }
      ]
    },
    {
      "time": "10:00",
      "datetime": "2026-06-26T10:00:00",
      "gate": "D13",
      "flight_code": "BR707",
      "airline_code": "BR",
      "airline_name": "長榮航空",
      "type": "departure",
      "airport_code": "CAN",
      "city": "Guangzhou",
      "status": "出發DEPARTED",
      "aircraft": "B777-300",
      "terminal": "2",
      "destination": "Guangzhou (CAN)",
      "codeshare_flights": [
        {
          "flight_code": "HU8122",
          "airline_code": "HU",
          "airline_name": "海南航空"
        }
      ]
    },
    {
      "time": "12:30",
      "datetime": "2026-06-26T12:30:00",
      "gate": "D12",
      "flight_code": "CI104",
      "airline_code": "CI",
      "airline_name": "中華航空",
      "type": "departure",
      "airport_code": "NRT",
      "city": "Tokyo",
      "status": "出發DEPARTED",
      "aircraft": "A330-300",
      "terminal": "2",
      "destination": "Tokyo (NRT)",
      "codeshare_flights": [
        {
          "flight_code": "JL5176",
          "airline_code": "JL",
          "airline_name": "日本航空"
        },
        {
          "flight_code": "QF8738",
          "airline_code": "QF",
          "airline_name": "澳洲航空"
        }
      ]
    },
    {
      "time": "14:15",
      "datetime": "2026-06-26T14:15:00",
      "gate": "D11",
      "flight_code": "JX713",
      "airline_code": "JX",
      "airline_name": "星宇航空",
      "type": "departure",
      "airport_code": "SGN",
      "city": "Ho Chi Minh",
      "status": "出發DEPARTED",
      "aircraft": "A321-252",
      "terminal": "2",
      "destination": "Ho Chi Minh (SGN)",
      "codeshare_flights": []
    },
    {
      "time": "14:20",
      "datetime": "2026-06-26T14:20:00",
      "gate": "D12",
      "flight_code": "CI172",
      "airline_code": "CI",
      "airline_name": "中華航空",
      "type": "departure",
      "airport_code": "KIX",
      "city": "Osaka Kansai",
      "status": "出發DEPARTED",
      "aircraft": "B777-300",
      "terminal": "2",
      "destination": "Osaka Kansai (KIX)",
      "codeshare_flights": [
        {
          "flight_code": "JL5106",
          "airline_code": "JL",
          "airline_name": "日本航空"
        }
      ]
    },
    {
      "time": "14:20",
      "datetime": "2026-06-26T14:20:00",
      "gate": "D16",
      "flight_code": "BR176",
      "airline_code": "BR",
      "airline_name": "長榮航空",
      "type": "departure",
      "airport_code": "UKB",
      "city": "KOBE",
      "status": "出發DEPARTED",
      "aircraft": "A321-200",
      "terminal": "2",
      "destination": "KOBE (UKB)",
      "codeshare_flights": []
    },
    {
      "time": "14:35",
      "datetime": "2026-06-26T14:35:00",
      "gate": "D14R",
      "flight_code": "CI108",
      "airline_code": "CI",
      "airline_name": "中華航空",
      "type": "departure",
      "airport_code": "NRT",
      "city": "Tokyo",
      "status": "出發DEPARTED",
      "aircraft": "A321-271",
      "terminal": "2",
      "destination": "Tokyo (NRT)",
      "codeshare_flights": [
        {
          "flight_code": "QF8740",
          "airline_code": "QF",
          "airline_name": "澳洲航空"
        },
        {
          "flight_code": "JL5048",
          "airline_code": "JL",
          "airline_name": "日本航空"
        }
      ]
    },
    {
      "time": "14:40",
      "datetime": "2026-06-26T14:40:00",
      "gate": "D15R",
      "flight_code": "BR385",
      "airline_code": "BR",
      "airline_name": "長榮航空",
      "type": "departure",
      "airport_code": "HAN",
      "city": "Hanoi",
      "status": "出發DEPARTED",
      "aircraft": "A321-200",
      "terminal": "2",
      "destination": "Hanoi (HAN)",
      "codeshare_flights": [
        {
          "flight_code": "TK9474",
          "airline_code": "TK",
          "airline_name": "土耳其航空"
        }
      ]
    },
    {
      "time": "15:00",
      "datetime": "2026-06-26T15:00:00",
      "gate": "D18",
      "flight_code": "JX705",
      "airline_code": "JX",
      "airline_name": "星宇航空",
      "type": "departure",
      "airport_code": "PQC",
      "city": "Phu Quoc",
      "status": "出發DEPARTED",
      "aircraft": "A321-252",
      "terminal": "2",
      "destination": "Phu Quoc (PQC)",
      "codeshare_flights": []
    },
    {
      "time": "15:15",
      "datetime": "2026-06-26T15:15:00",
      "gate": "D13",
      "flight_code": "BR160",
      "airline_code": "BR",
      "airline_name": "長榮航空",
      "type": "departure",
      "airport_code": "ICN",
      "city": "Incheon",
      "status": "出發DEPARTED",
      "aircraft": "B787-10",
      "terminal": "2",
      "destination": "Incheon (ICN)",
      "codeshare_flights": [
        {
          "flight_code": "TK9547",
          "airline_code": "TK",
          "airline_name": "土耳其航空"
        },
        {
          "flight_code": "TG6392",
          "airline_code": "TG",
          "airline_name": "泰國航空"
        },
        {
          "flight_code": "B77026",
          "airline_code": "B7",
          "airline_name": "立榮航空"
        },
        {
          "flight_code": "OZ6872",
          "airline_code": "OZ",
          "airline_name": "韓亞航空"
        },
        {
          "flight_code": "NZ4922",
          "airline_code": "NZ",
          "airline_name": "紐西蘭航空"
        }
      ]
    },
    {
      "time": "16:25",
      "datetime": "2026-06-26T16:25:00",
      "gate": "D11",
      "flight_code": "B7187",
      "airline_code": "B7",
      "airline_name": "立榮航空",
      "type": "departure",
      "airport_code": "SZX",
      "city": "Shenzhen",
      "status": "出發DEPARTED",
      "aircraft": "B777-300",
      "terminal": "2",
      "destination": "Shenzhen (SZX)",
      "codeshare_flights": [
        {
          "flight_code": "ZH3402",
          "airline_code": "ZH",
          "airline_name": "深圳航空"
        }
      ]
    },
    {
      "time": "16:40",
      "datetime": "2026-06-26T16:40:00",
      "gate": "D15R",
      "flight_code": "BR871",
      "airline_code": "BR",
      "airline_name": "長榮航空",
      "type": "departure",
      "airport_code": "HKG",
      "city": "Hong Kong",
      "status": "出發DEPARTED",
      "aircraft": "B777-300",
      "terminal": "2",
      "destination": "Hong Kong (HKG)",
      "codeshare_flights": [
        {
          "flight_code": "HX1831",
          "airline_code": "HX",
          "airline_name": "香港航空"
        }
      ]
    },
    {
      "time": "17:30",
      "datetime": "2026-06-26T17:30:00",
      "gate": "D12",
      "flight_code": "CI36",
      "airline_code": "CI",
      "airline_name": "中華航空",
      "type": "departure",
      "airport_code": "PHX",
      "city": "Phoenix",
      "status": "準時ON TIME",
      "aircraft": "B777-300",
      "terminal": "2",
      "destination": "Phoenix (PHX)",
      "codeshare_flights": []
    },
    {
      "time": "20:10",
      "datetime": "2026-06-26T20:10:00",
      "gate": "D12",
      "flight_code": "JX32",
      "airline_code": "JX",
      "airline_name": "星宇航空",
      "type": "departure",
      "airport_code": "SEA",
      "city": "Seattle",
      "status": "準時ON TIME",
      "aircraft": "A350-900",
      "terminal": "2",
      "destination": "Seattle (SEA)",
      "codeshare_flights": []
    },
    {
      "time": "20:45",
      "datetime": "2026-06-26T20:45:00",
      "gate": "D13",
      "flight_code": "BR205",
      "airline_code": "BR",
      "airline_name": "長榮航空",
      "type": "departure",
      "airport_code": "BKK",
      "city": "Bangkok",
      "status": "準時ON TIME",
      "aircraft": "B787-10",
      "terminal": "2",
      "destination": "Bangkok (BKK)",
      "codeshare_flights": [
        {
          "flight_code": "AI7063",
          "airline_code": "AI",
          "airline_name": "印度航空"
        },
        {
          "flight_code": "TK9458",
          "airline_code": "TK",
          "airline_name": "土耳其航空"
        },
        {
          "flight_code": "TG6307",
          "airline_code": "TG",
          "airline_name": "泰國航空"
        }
      ]
    }
  ],
  "summary": {
    "total_flights": 31,
    "before_17:00": 28,
    "after_17:00": 3
  },
  "formatted_display": [
    "00:05 : D16 : JX12 (星宇航空)",
    "00:10 : D15R : JX2 (星宇航空)",
    "06:20 : D13 : BR134 (長榮航空)",
    "06:30 : D17 : BR217 (長榮航空)",
    "06:55 : D18 : JX761 (星宇航空)",
    "07:00 : D15R : BR891 (長榮航空)",
    "07:30 : D13 : CI154 (中華航空)",
    "07:30 : D16 : BR170 (長榮航空)",
    "08:10 : D11 : JX771 (星宇航空)",
    "08:15 : D17 : BR851 (長榮航空)",
    "08:20 : D12 : BR132 (長榮航空)",
    "08:40 : D15R : CI501 (中華航空)",
    "09:00 : D18 : BR198 (長榮航空)",
    "09:00 : D14R : BR237 (長榮航空)",
    "09:00 : D16 : BR397 (長榮航空)",
    "09:50 : D11 : BR255 (長榮航空)",
    "09:55 : D12 : BR712 (長榮航空)",
    "10:00 : D13 : BR707 (長榮航空)",
    "12:30 : D12 : CI104 (中華航空)",
    "14:15 : D11 : JX713 (星宇航空)",
    "14:20 : D12 : CI172 (中華航空)",
    "14:20 : D16 : BR176 (長榮航空)",
    "14:35 : D14R : CI108 (中華航空)",
    "14:40 : D15R : BR385 (長榮航空)",
    "15:00 : D18 : JX705 (星宇航空)",
    "15:15 : D13 : BR160 (長榮航空)",
    "16:25 : D11 : B7187 (立榮航空)",
    "16:40 : D15R : BR871 (長榮航空)",
    "17:30 : D12 : CI36 (中華航空)",
    "20:10 : D12 : JX32 (星宇航空)",
    "20:45 : D13 : BR205 (長榮航空)"
  ],
  "updated_at": "2026-06-26T09:40:12.387345"
}